lingodbbridge/__init__.py
lingodbbridge/ext.cpython-310-x86_64-linux-gnu.so
lingodbbridge/libs/libpybridge.so
lingodbbridge/mlir/ir.py
lingodbbridge/mlir/_mlir_libs/_mlir.cpython-310-x86_64-linux-gnu.so
lingodbbridge/mlir/_mlir_libs/mlir_init.cpython-310-x86_64-linux-gnu.so
lingodbbridge/mlir/_mlir_libs/mlir_lingodb.cpython-310-x86_64-linux-gnu.so
lingodbbridge/mlir/dialects/_arith_enum_gen.py
lingodbbridge/mlir/dialects/_arith_ops_gen.py
lingodbbridge/mlir/dialects/_builtin_ops_gen.py
lingodbbridge/mlir/dialects/_db_enum_gen.py
lingodbbridge/mlir/dialects/_db_ops_gen.py
lingodbbridge/mlir/dialects/_func_ops_gen.py
lingodbbridge/mlir/dialects/_ods_common.py
lingodbbridge/mlir/dialects/_relalg_enum_gen.py
lingodbbridge/mlir/dialects/_relalg_ops_gen.py
lingodbbridge/mlir/dialects/_scf_ops_gen.py
lingodbbridge/mlir/dialects/_subop_enum_gen.py
lingodbbridge/mlir/dialects/_subop_ops_gen.py
lingodbbridge/mlir/dialects/_tuples_ops_gen.py
lingodbbridge/mlir/dialects/_util_ops_gen.py
lingodbbridge/mlir/dialects/arith.py
lingodbbridge/mlir/dialects/builtin.py
lingodbbridge/mlir/dialects/db.py
lingodbbridge/mlir/dialects/func.py
lingodbbridge/mlir/dialects/relalg.py
lingodbbridge/mlir/dialects/scf.py
lingodbbridge/mlir/dialects/subop.py
lingodbbridge/mlir/dialects/tuples.py
lingodbbridge/mlir/dialects/util.py
lingodbbridge/mlir/extras/meta.py
lingodbbridge/mlir/extras/types.py
lingodb_bridge-0.0.4.dist-info/METADATA
lingodb_bridge-0.0.4.dist-info/WHEEL
lingodb_bridge-0.0.4.dist-info/RECORD
