Metadata-Version: 2.2
Name: lingodb-bridge
Version: 0.0.4
Requires-Dist: numpy===1.26.4
Requires-Dist: pyarrow===20.0.0
